mongo_path/__init__.py
mongo_path/field_repr.py
mongo_path/meta.py
mongo_path/mongo_string.py
mongo_path/path_generator.py
mongo_path/printester.py
mongo_path/typing_utils.py
mongo_path-1.1.0.dist-info/LICENSE
mongo_path-1.1.0.dist-info/METADATA
mongo_path-1.1.0.dist-info/WHEEL
mongo_path-1.1.0.dist-info/top_level.txt
mongo_path-1.1.0.dist-info/RECORD
