Metadata-Version: 2.1
Name: mongo-path
Version: 1.1.0
Keywords: MongoDB,pydantic
Requires-Python: >=3.10
License-File: LICENSE
Requires-Dist: pydantic ~=2.3.0
